fastdi/__init__.py
fastdi/_container.py
fastdi/_errors.py
fastdic-0.0.1.dist-info/LICENSE
fastdic-0.0.1.dist-info/METADATA
fastdic-0.0.1.dist-info/WHEEL
fastdic-0.0.1.dist-info/top_level.txt
fastdic-0.0.1.dist-info/RECORD
